<?xml version="1.0" encoding="UTF-8" ?>

<!-- 
 * tiles_es.xml
 *
 * Copyright (C) 2017 Universidad de Sevilla
 * 
 * The use of this project is hereby constrained to the conditions of the 
 * TDG Licence, a copy of which you may download from 
 * http://www.tdg-seville.info/License.html
 -->

<!DOCTYPE tiles-definitions PUBLIC
       "-//Apache Software Foundation//DTD Tiles Configuration 2.0//EN"
       "http://tiles.apache.org/dtds/tiles-config_2_0.dtd">
      
<tiles-definitions>

	<definition name="tag/list" extends="master.page">	
		<put-attribute name="title" value="List of tags" />
		<put-attribute name="body" value="/views/tag/list.jsp" />
	</definition>
	
	<definition name="tag/edit" extends="master.page">	
		<put-attribute name="title" value="Edit Tag" />
		<put-attribute name="body" value="/views/tag/edit.jsp" />
	</definition>
	
	<definition name="tag/associaton" extends="master.page">	
		<put-attribute name="title" value="Assiciation Tag" />
		<put-attribute name="body" value="/views/tag/association.jsp" />
	</definition>
	
	<definition name="tag/add" extends="master.page">	
		<put-attribute name="title" value="Add Tag" />
		<put-attribute name="body" value="/views/tag/add.jsp" />
	</definition>


</tiles-definitions>